tiledb/cloud/__init__.py
tiledb/cloud/array.py
tiledb/cloud/asset.py
tiledb/cloud/client.py
tiledb/cloud/cloudarray.py
tiledb/cloud/config.py
tiledb/cloud/groups.py
tiledb/cloud/invites.py
tiledb/cloud/notebook.py
tiledb/cloud/pool_manager_wrapper.py
tiledb/cloud/tasks.py
tiledb/cloud/tiledb_cloud_error.py
tiledb/cloud/udf.py
tiledb/cloud/utils.py
tiledb/cloud/version.py
tiledb/cloud/_common/__init__.py
tiledb/cloud/_common/_array_backed.py
tiledb/cloud/_common/functions.py
tiledb/cloud/_common/futures.py
tiledb/cloud/_common/json_safe.py
tiledb/cloud/_common/ordered.py
tiledb/cloud/_common/pickle_compat.py
tiledb/cloud/_common/testonly.py
tiledb/cloud/_common/trampoline.py
tiledb/cloud/_common/utils.py
tiledb/cloud/_common/visitor.py
tiledb/cloud/_common/api_v2/__init__.py
tiledb/cloud/_common/api_v2/api_client.py
tiledb/cloud/_common/api_v2/configuration.py
tiledb/cloud/_common/api_v2/exceptions.py
tiledb/cloud/_common/api_v2/rest.py
tiledb/cloud/_common/api_v2/api/__init__.py
tiledb/cloud/_common/api_v2/api/array_api.py
tiledb/cloud/_common/api_v2/api/files_api.py
tiledb/cloud/_common/api_v2/api/groups_api.py
tiledb/cloud/_common/api_v2/api/notebooks_api.py
tiledb/cloud/_common/api_v2/api/organization_api.py
tiledb/cloud/_common/api_v2/api/query_api.py
tiledb/cloud/_common/api_v2/api/user_api.py
tiledb/cloud/_common/api_v2/models/__init__.py
tiledb/cloud/_common/api_v2/models/access_credential.py
tiledb/cloud/_common/api_v2/models/access_credential_credential.py
tiledb/cloud/_common/api_v2/models/access_credential_role.py
tiledb/cloud/_common/api_v2/models/access_credential_token.py
tiledb/cloud/_common/api_v2/models/access_credential_type.py
tiledb/cloud/_common/api_v2/models/access_credentials_data.py
tiledb/cloud/_common/api_v2/models/activity_event_type.py
tiledb/cloud/_common/api_v2/models/array.py
tiledb/cloud/_common/api_v2/models/array_activity_log.py
tiledb/cloud/_common/api_v2/models/array_activity_log_data.py
tiledb_cloud-2024.1.dist-info/LICENSE
tiledb_cloud-2024.1.dist-info/METADATA
tiledb_cloud-2024.1.dist-info/WHEEL
tiledb_cloud-2024.1.dist-info/top_level.txt
tiledb_cloud-2024.1.dist-info/RECORD
