Metadata-Version: 2.1
Name: tiledb-cloud
Version: 2024.1
Summary: TileDB Cloud platform Python client
Project-URL: homepage, https://tiledb.com
Project-URL: repository, https://github.com/TileDB-Inc/TileDB-Cloud-Py
Requires-Python: >=3.8
License-File: LICENSE
Requires-Dist: anndata
Requires-Dist: attrs>=21.4.0
Requires-Dist: certifi
Requires-Dist: cloudpickle<3,>=1.4.1
Requires-Dist: importlib-metadata
Requires-Dist: packaging
Requires-Dist: pandas>=1.2.4
Requires-Dist: pyarrow>=3.0.0
Requires-Dist: python-dateutil
Requires-Dist: six>=1.10
Requires-Dist: tblib~=1.7
Requires-Dist: tiledb>=0.15.2
Requires-Dist: typing-extensions
Requires-Dist: urllib3>=1.26
Provides-Extra: all
Requires-Dist: networkx>=2; extra == "all"
Requires-Dist: plotly>=4; extra == "all"
Requires-Dist: pydot<3; extra == "all"
Requires-Dist: tiledb-plot-widget>=0.1.7; extra == "all"
Provides-Extra: dev
Requires-Dist: black; extra == "dev"
Requires-Dist: pytest; extra == "dev"
Requires-Dist: ruff; extra == "dev"
Provides-Extra: docs
Requires-Dist: quartodoc; extra == "docs"
Provides-Extra: life-sciences
Requires-Dist: tiledbsoma; extra == "life-sciences"
Provides-Extra: tests
Requires-Dist: xarray; extra == "tests"
Requires-Dist: pytest-cov; extra == "tests"
Requires-Dist: pytest-explicit; extra == "tests"
Requires-Dist: pytest-split; extra == "tests"
Requires-Dist: tiledbsoma; extra == "tests"
Provides-Extra: viz-plotly
Requires-Dist: networkx>=2; extra == "viz-plotly"
Requires-Dist: plotly>=4; extra == "viz-plotly"
Requires-Dist: pydot<3; extra == "viz-plotly"
Provides-Extra: viz-tiledb
Requires-Dist: networkx>=2; extra == "viz-tiledb"
Requires-Dist: pydot<3; extra == "viz-tiledb"
Requires-Dist: tiledb-plot-widget>=0.1.7; extra == "viz-tiledb"
